loggingpkg/__init__.py
loggingpkg/config.py
loggingpkg/handlers.py
loggingpkg-1.2.1.dist-info/LICENSE.txt
loggingpkg-1.2.1.dist-info/METADATA
loggingpkg-1.2.1.dist-info/WHEEL
loggingpkg-1.2.1.dist-info/top_level.txt
loggingpkg-1.2.1.dist-info/RECORD
