Metadata-Version: 2.1
Name: loggingpkg
Version: 1.2.1
Summary: A simple logging python package
Author: musicmuser32
Author-email: musicmuser32@gmail.com
Classifier: Programming Language :: Python :: 3
Classifier: License :: OSI Approved :: MIT License
Classifier: Operating System :: OS Independent
Requires-Python: >=3.6
License-File: LICENSE.txt
